pysat/__init__.py
pysat/_constellation.py
pysat/_custom.py
pysat/_files.py
pysat/_instrument.py
pysat/_meta.py
pysat/_orbits.py
pysat/model_utils.py
pysat/version.txt
pysat/constellations/__init__.py
pysat/constellations/icon.py
pysat/constellations/single_test.py
pysat/constellations/test_add_opposite.py
pysat/constellations/test_add_similar.py
pysat/constellations/test_diff_same.py
pysat/constellations/test_diff_similar.py
pysat/constellations/testing.py
pysat/constellations/testing_empty.py
pysat/instruments/__init__.py
pysat/instruments/champ_star.py
pysat/instruments/cnofs_ivm.py
pysat/instruments/cnofs_plp.py
pysat/instruments/cnofs_vefi.py
pysat/instruments/cosmic_gps.py
pysat/instruments/demeter_iap.py
pysat/instruments/dmsp_ivm.py
pysat/instruments/icon_euv.py
pysat/instruments/icon_fuv.py
pysat/instruments/icon_ivm.py
pysat/instruments/icon_mighti.py
pysat/instruments/iss_fpmu.py
pysat/instruments/jro_isr.py
pysat/instruments/omni_hro.py
pysat/instruments/pysat_testing.py
pysat/instruments/pysat_testing2d.py
pysat/instruments/pysat_testing2d_xarray.py
pysat/instruments/pysat_testing_xarray.py
pysat/instruments/rocsat1_ivm.py
pysat/instruments/sport_ivm.py
pysat/instruments/superdarn_grdex.py
pysat/instruments/supermag_magnetometer.py
pysat/instruments/sw_dst.py
pysat/instruments/sw_f107.py
pysat/instruments/sw_kp.py
pysat/instruments/timed_saber.py
pysat/instruments/timed_see.py
pysat/instruments/ucar_tiegcm.py
pysat/instruments/methods/__init__.py
pysat/instruments/methods/demeter.py
pysat/instruments/methods/madrigal.py
pysat/instruments/methods/nasa_cdaweb.py
pysat/instruments/methods/sw.py
pysat/instruments/methods/testing.py
pysat/instruments/templates/madrigal_pandas.py
pysat/instruments/templates/netcdf_pandas.py
pysat/instruments/templates/template_cdaweb_instrument.py
pysat/instruments/templates/template_instrument.py
pysat/ssnl/__init__.py
pysat/ssnl/_core.py
pysat/ssnl/avg.py
pysat/ssnl/occur_prob.py
pysat/ssnl/plot.py
pysat/utils/__init__.py
pysat-2.1.0.dist-info/LICENSE
pysat-2.1.0.dist-info/METADATA
pysat-2.1.0.dist-info/WHEEL
pysat-2.1.0.dist-info/top_level.txt
pysat-2.1.0.dist-info/RECORD
