Metadata-Version: 2.1
Name: pysat
Version: 2.1.0
Summary: Supports science data analysis across measurement platforms
Home-page: http://github.com/pysat/pysat
Author: Russell Stoneback
Author-email: rstoneba@utdallas.edu
License: BSD
Platform: UNKNOWN
Classifier: Development Status :: 5 - Production/Stable
Classifier: Intended Audience :: Science/Research
Classifier: Topic :: Scientific/Engineering :: Astronomy
Classifier: Topic :: Scientific/Engineering :: Physics
Classifier: Topic :: Scientific/Engineering :: Atmospheric Science
Classifier: License :: OSI Approved :: BSD License
Classifier: Programming Language :: Python :: 2.7
Classifier: Programming Language :: Python :: 3.4
Classifier: Programming Language :: Python :: 3.5
Classifier: Programming Language :: Python :: 3.6
Classifier: Programming Language :: Python :: 3.7
Requires-Dist: requests
Requires-Dist: beautifulsoup4
Requires-Dist: lxml
Requires-Dist: netCDF4
Requires-Dist: xarray (<0.12)
Requires-Dist: pandas (<0.25,>=0.23)
Requires-Dist: numpy (<1.17,>=1.12)
Requires-Dist: scipy (<1.3)
Requires-Dist: matplotlib (<3.0)
Requires-Dist: pysatCDF
Requires-Dist: madrigalWeb
Requires-Dist: h5py
Requires-Dist: PyForecastTools
